{
"frames": {
	"icedrake_04.png": {
		"frame": {"x":185, "y":188, "w":133, "h":76},
		"spriteSourceSize": {"x":0,"y":0,"w":133,"h":76},
		"sourceSize": {"w":133,"h":76}
	},
	"icedrake_05.png": {
		"frame": {"x":186, "y":0, "w":127, "h":82},
		"spriteSourceSize": {"x":0,"y":0,"w":127,"h":82},
		"sourceSize": {"w":127,"h":82}
	},
	"icedrake_06.png": {
		"frame": {"x":314, "y":0, "w":124, "h":78},
		"spriteSourceSize": {"x":0,"y":0,"w":124,"h":78},
		"sourceSize": {"w":124,"h":78}
	},
	"icedrake_07.png": {
		"frame": {"x":186, "y":83, "w":126, "h":83},
		"spriteSourceSize": {"x":0,"y":0,"w":126,"h":83},
		"sourceSize": {"w":126,"h":83}
	},
	"icedrake_08.png": {
		"frame": {"x":313, "y":83, "w":124, "h":97},
		"spriteSourceSize": {"x":0,"y":0,"w":124,"h":97},
		"sourceSize": {"w":124,"h":97}
	},
	"icedrake_19.png": {
		"frame": {"x":0, "y":282, "w":164, "h":93},
		"spriteSourceSize": {"x":22,"y":0,"w":186,"h":93},
		"sourceSize": {"w":186,"h":93}
	},
	"icedrake_20.png": {
		"frame": {"x":0, "y":0, "w":185, "h":93},
		"spriteSourceSize": {"x":1,"y":0,"w":186,"h":93},
		"sourceSize": {"w":186,"h":93}
	},
	"icedrake_21.png": {
		"frame": {"x":0, "y":188, "w":184, "h":93},
		"spriteSourceSize": {"x":2,"y":0,"w":186,"h":93},
		"sourceSize": {"w":186,"h":93}
	},
	"icedrake_22.png": {
		"frame": {"x":0, "y":94, "w":185, "h":93},
		"spriteSourceSize": {"x":1,"y":0,"w":186,"h":93},
		"sourceSize": {"w":186,"h":93}
	},
	"icedrake_23.png": {
		"frame": {"x":165, "y":282, "w":151, "h":93},
		"spriteSourceSize": {"x":35,"y":0,"w":186,"h":93},
		"sourceSize": {"w":186,"h":93}
	},
	"icedrake_24.png": {
		"frame": {"x":0, "y":376, "w":102, "h":23},
		"spriteSourceSize": {"x":0,"y":0,"w":102,"h":23},
		"sourceSize": {"w":102,"h":23}
	},
	"icedrake_25.png": {
		"frame": {"x":0, "y":400, "w":95, "h":23},
		"spriteSourceSize": {"x":0,"y":0,"w":95,"h":23},
		"sourceSize": {"w":95,"h":23}
	},
	"icedrake_26.png": {
		"frame": {"x":96, "y":400, "w":90, "h":19},
		"spriteSourceSize": {"x":0,"y":0,"w":90,"h":19},
		"sourceSize": {"w":90,"h":19}
	}

},
"meta": {
	"image": "icedrake.png",
	"size": {"w": 439, "h": 424},
	"scale": "1"
}
}